ai_exam/__init__.py
ai_exam/knowledge.py
ai_exam/optimization.py
ai_exam/search.py
ai_exam-0.0.1.dist-info/LICENSE
ai_exam-0.0.1.dist-info/METADATA
ai_exam-0.0.1.dist-info/WHEEL
ai_exam-0.0.1.dist-info/top_level.txt
ai_exam-0.0.1.dist-info/RECORD
