Metadata-Version: 2.1
Name: ai-exam
Version: 0.0.1
Summary: ai_exam
Home-page: UNKNOWN
Author: harsh
Author-email: ghatiyaharsh@gmail.com
License: UNKNOWN
Keywords: knowledge,optimization,search
Platform: UNKNOWN
Classifier: Development Status :: 1 - Planning
Classifier: Intended Audience :: Developers
Classifier: Programming Language :: Python :: 3
Classifier: Operating System :: Unix
Classifier: Operating System :: MacOS :: MacOS X
Classifier: Operating System :: Microsoft :: Windows
License-File: LICENSE
